autowindows/__init__.py
autowindows/autowindows.py
comtypes/GUID.py
comtypes/__init__.py
comtypes/_comobject.py
comtypes/_memberspec.py
comtypes/_meta.py
comtypes/_npsupport.py
comtypes/_safearray.py
comtypes/_tlib_version_checker.py
comtypes/_vtbl.py
comtypes/automation.py
comtypes/clear_cache.py
comtypes/connectionpoints.py
comtypes/errorinfo.py
comtypes/git.py
comtypes/hints.pyi
comtypes/hresult.py
comtypes/logutil.py
comtypes/messageloop.py
comtypes/patcher.py
comtypes/persist.py
comtypes/safearray.py
comtypes/shelllink.py
comtypes/stream.py
comtypes/typeinfo.py
comtypes/util.py
comtypes/viewobject.py
comtypes/_post_coinit/__init__.py
comtypes/_post_coinit/_cominterface_meta_patcher.py
comtypes/_post_coinit/bstr.py
comtypes/_post_coinit/instancemethod.py
comtypes/_post_coinit/misc.py
comtypes/_post_coinit/unknwn.py
comtypes/client/__init__.py
comtypes/client/_activeobj.py
comtypes/client/_code_cache.py
comtypes/client/_constants.py
comtypes/client/_create.py
comtypes/client/_events.py
comtypes/client/_generate.py
comtypes/client/_managing.py
comtypes/client/dynamic.py
comtypes/client/lazybind.py
comtypes/server/__init__.py
comtypes/server/automation.py
comtypes/server/connectionpoints.py
comtypes/server/inprocserver.py
comtypes/server/localserver.py
comtypes/server/register.py
comtypes/server/w_getopt.py
comtypes/test/TestComServer.py
comtypes/test/TestDispServer.py
comtypes/test/__init__.py
comtypes/test/find_memleak.py
comtypes/test/runtests.py
comtypes/test/setup.py
comtypes/test/test_BSTR.py
comtypes/test/test_DISPPARAMS.py
comtypes/test/test_GUID.py
comtypes/test/test_QueryService.py
comtypes/test/test_agilent.py
comtypes/test/test_avmc.py
comtypes/test/test_basic.py
comtypes/test/test_casesensitivity.py
comtypes/test/test_clear_cache.py
comtypes/test/test_client.py
comtypes/test/test_client_dynamic.py
comtypes/test/test_client_regenerate_modules.py
comtypes/test/test_collections.py
comtypes/test/test_comobject.py
comtypes/test/test_comserver.py
autowindows-0.1.1.dist-info/METADATA
autowindows-0.1.1.dist-info/WHEEL
autowindows-0.1.1.dist-info/top_level.txt
autowindows-0.1.1.dist-info/RECORD
